qnverter/qnverter.py
Qnverter-1.2.4.dist-info/LICENSE
Qnverter-1.2.4.dist-info/METADATA
Qnverter-1.2.4.dist-info/WHEEL
Qnverter-1.2.4.dist-info/entry_points.txt
Qnverter-1.2.4.dist-info/top_level.txt
Qnverter-1.2.4.dist-info/RECORD
