Metadata-Version: 2.1
Name: Qnverter
Version: 1.2.4
Summary: Python application for quick text conversions.
Home-page: https://github.com/Nicky5/Qnverter
Author: nicky
Author-email: vandini.elia@gmail.com
License: MIT
Platform: UNKNOWN
License-File: LICENSE
Requires-Dist: certifi
Requires-Dist: charset-normalizer
Requires-Dist: idna
Requires-Dist: PyQt5
Requires-Dist: requests
Requires-Dist: urllib3
